big_scatter/__init__.py
big_scatter-0.1.4.dist-info/licenses/LICENSE
big_scatter-0.1.4.dist-info/METADATA
big_scatter-0.1.4.dist-info/WHEEL
big_scatter-0.1.4.dist-info/top_level.txt
big_scatter-0.1.4.dist-info/RECORD
