Metadata-Version: 2.4
Name: big_scatter
Version: 0.1.4
Summary: Simple jupyter widget to draw and explore a large set of 2D datapoints.
Author-email: Benoit Favre <benoit.favre@gmail.com>
License-Expression: MIT
Project-URL: Homepage, https://github.com/benob/big_scatter
Project-URL: Issues, https://github.com/benob/big_scatter/issues
Requires-Python: >=3.6
License-File: LICENSE
Requires-Dist: IPython
Dynamic: license-file
